setup.py
awsenv/__init__.py
awsenv/cache.py
awsenv/main.py
awsenv/profile.py
awsenv.egg-info/PKG-INFO
awsenv.egg-info/SOURCES.txt
awsenv.egg-info/dependency_links.txt
awsenv.egg-info/entry_points.txt
awsenv.egg-info/requires.txt
awsenv.egg-info/top_level.txt