Metadata-Version: 1.0
Name: awsenv
Version: 1.12.1
Summary: AWS profile and session management from the CLI
Home-page: http://locationlabs.com
Author: Location Labs
Author-email: info@locationlabs.com
License: UNKNOWN
Platform: UNKNOWN
